pozansky_news_server/__init__.py
pozansky_news_server/__main__.py
pozansky_news_server/server.py
pozansky_news_server-1.6.0.dist-info/METADATA
pozansky_news_server-1.6.0.dist-info/WHEEL
pozansky_news_server-1.6.0.dist-info/entry_points.txt
pozansky_news_server-1.6.0.dist-info/RECORD
