Metadata-Version: 2.4
Name: pozansky_news_server
Version: 1.6.0
Summary: news-server
Requires-Python: >=3.12
Requires-Dist: beautifulsoup4>=4.12.3
Requires-Dist: build>=1.2.2.post1
Requires-Dist: feedparser>=6.0.0
Requires-Dist: html2text>=2024.2.26
Requires-Dist: httpx>=0.25.0
Requires-Dist: mcp[cli]>=1.2.0
Requires-Dist: requests>=2.32.3
Requires-Dist: twine>=6.1.0
